jetson_serial/__init__.py
jetson_serial/jetson_serial.py
jetson_serial/jetson_serial_util.py
jetson_utils/__init__.py
jetson_utils/jetson_utils.py
test/__init__.py
jetson_utils-0.0.10.dist-info/LICENSE
jetson_utils-0.0.10.dist-info/METADATA
jetson_utils-0.0.10.dist-info/WHEEL
jetson_utils-0.0.10.dist-info/top_level.txt
jetson_utils-0.0.10.dist-info/RECORD
