Metadata-Version: 2.1
Name: jetson-utils
Version: 0.0.10
Summary: Jetson Utility
Home-page: UNKNOWN
Author: Jai-Chang.Park(Dreamwalker)
Author-email: jaichang@angel-robotics.com
License: Apache
Platform: UNKNOWN
Classifier: Programming Language :: Python :: 3
Classifier: License :: OSI Approved :: MIT License
Classifier: Operating System :: OS Independent
Requires-Python: >=3.6
License-File: LICENSE
Requires-Dist: jetson-stats
